{"id":"485","row":"485","title":"Piscou e já era: Veja Limpa Vidros Vidrex Tradicional - Fórmula de lavagem de vidro, 500ml","slug":"veja-limpa-vidros-vi-485","excerpt":"Piscou e já era: Veja Limpa Vidros Vidrex Tradicional - Fórmula de lavagem de vidro, 500ml","category":"Casa","categorySlug":"casa","coverImage":"https://m.media-amazon.com/images/I/41AaUcjkKAL._SL500_.jpg","publishedAt":"2025-08-08T20:47:44.281Z","productLink":"https://www.amazon.com.br/dp/B07DYYC9P9?tag=drsv00-20&linkCode=osi&th=1&psc=1","productAsin":"B07DYYC9P9","productBarcode":"7891035800207","content":[{"type":"text","content":"<p>Olha só o que eu encontrei:</p>"},{"type":"product","product":{"title":"Veja Limpa Vidros Vidrex Tradicional - Fórmula de lavagem de vidro, 500ml","description":"Oferece brilho e limpeza profunda, Ideal para superfícies como vidros, vitrines, para-brisas, espelhos, Capaz de remover sujeiras como fuligem, marcas de dedos e poeira, Secagem Rápida, Contém Álcool, Para a limpeza diária, aplique o produto nas superfícies sujas a uma distância de aproximadamente 30 cm.","price":9.79,"image":"https://m.media-amazon.com/images/I/41AaUcjkKAL._SL500_.jpg","affiliateLink":"https://www.amazon.com.br/dp/B07DYYC9P9?tag=drsv00-20&linkCode=osi&th=1&psc=1"}},{"type":"text","content":"<p>Espero que tenha gostado — até a próxima!</p>"}]}