{"id":"377","row":"377","title":"O que está fazendo sucesso: KIT 5 Potes de Vidro Retangular com Tampa Hermética 640ml Cor:Azul (QH)","slug":"kit-5-potes-de-vidro-377","excerpt":"O que está fazendo sucesso: KIT 5 Potes de Vidro Retangular com Tampa Hermética 640ml Cor:Azul (QH)","category":"Cozinha","categorySlug":"cozinha","coverImage":"https://m.media-amazon.com/images/I/41JRJO5FryL._SL500_.jpg","publishedAt":"2025-07-09T20:29:58.647Z","productLink":"https://www.amazon.com.br/dp/B08CPTZP2T?tag=drsv00-20&linkCode=osi&th=1&psc=1","productAsin":"B08CPTZP2T","productBarcode":"","content":[{"type":"text","content":"<p>Não dá pra perder essa oportunidade:</p>"},{"type":"product","product":{"title":"KIT 5 Potes de Vidro Retangular com Tampa Hermética 640ml Cor:Azul (QH)","description":"Anel de silicone removível, Possui 4 super travas, Mantém os alimentos frescos por mais tempo, Suporta uma variação térmica de até 300°C (não é indicado dar choque térmico), Evita que o cheiro se espalhe devido a sua super vedação","price":64.7,"image":"https://m.media-amazon.com/images/I/41JRJO5FryL._SL500_.jpg","affiliateLink":"https://www.amazon.com.br/dp/B08CPTZP2T?tag=drsv00-20&linkCode=osi&th=1&psc=1"}},{"type":"text","content":"<p>Valeu por passar aqui!</p>"}]}